module_level_lint/__init__.py
module_level_lint/error.py
module_level_lint/format.py
module_level_lint/lint.py
module_level_lint/utils.py
module_level_lint-0.2.2.dist-info/LICENSE
module_level_lint-0.2.2.dist-info/METADATA
module_level_lint-0.2.2.dist-info/WHEEL
module_level_lint-0.2.2.dist-info/entry_points.txt
module_level_lint-0.2.2.dist-info/RECORD
