Metadata-Version: 2.1
Name: module-level-lint
Version: 0.2.2
Summary: A Flake8 plugin to checking module level docstrings, future-imports, and dunders as specified in PEP 8
Home-page: https://github.com/hanhwanglim/module-level-lint
License: MIT
Keywords: flake8,lint
Author: Han Hwang Lim
Author-email: hanhwanglim@gmail.com
Requires-Python: >=3.9,<4.0
Classifier: Framework :: Flake8
Classifier: License :: OSI Approved :: MIT License
Classifier: Programming Language :: Python :: 3
Classifier: Programming Language :: Python :: 3.9
Classifier: Programming Language :: Python :: 3.10
Classifier: Programming Language :: Python :: 3.11
Classifier: Programming Language :: Python :: 3.12
Requires-Dist: flake8 (>=6.1.0,<8)
Project-URL: Repository, https://github.com/hanhwanglim/module-level-lint
